{
    "author": "Progress",
    "classifications": [
      "Universal"
    ],
    "name": "Page.Kendo.Angular.AddHeaderNav",
    "shortName": "Page.Kendo.Angular.AddHeaderNav",
    "identity": "Page.Kendo.Angular.AddHeaderNav",
    "tags": {
    "language": "Any",
    "type": "item",
    "wts.type": "composition",
    "wts.platform": "Web",
    "wts.version": "1.0.0",
    "wts.casing.sourceName": "kebab|pascal|camel",
    "wts.compositionFilter": "$frontendframework == KendoAngular & wts.type == page"
  },
    "sourceName": "wts.ItemName",
    "preferNameDirectory": true,
    "PrimaryOutputs": [
    ],
    "symbols": {
      "wts.rootNamespace": {
        "type": "parameter",
        "replaces": "Param_RootNamespace"
      },
      "wts.sourceName.casing.pascal": {
        "type": "parameter",
        "replaces": "Param_SourceName_Pascal"
      },
      "wts.sourceName.casing.kebab": {
        "type": "parameter",
        "replaces": "Param_SourceName_Kebab"
      },
      "wts.itemNamespace": {
        "type": "parameter",
        "replaces": "Param_ItemNamespace"
      }
    }
  }
